bromate/__init__.py
bromate/__main__.py
bromate/actions.py
bromate/agents.py
bromate/drivers.py
bromate/executions.py
bromate/interactions.py
bromate/scripts.py
bromate/settings.py
bromate/types.py
bromate-1.0.0.dist-info/LICENCE.txt
bromate-1.0.0.dist-info/METADATA
bromate-1.0.0.dist-info/WHEEL
bromate-1.0.0.dist-info/entry_points.txt
bromate-1.0.0.dist-info/RECORD
