Metadata-Version: 2.1
Name: bromate
Version: 1.0.0
Summary: Web browser automation through agentic workflows.
Home-page: https://github.com/fmind/bromate
License: MIT
Author: fmind
Requires-Python: >=3.12,<4.0
Classifier: License :: OSI Approved :: MIT License
Classifier: Programming Language :: Python :: 3
Classifier: Programming Language :: Python :: 3.12
Requires-Dist: google-generativeai (>=0.7.2,<0.8.0)
Requires-Dist: loguru (>=0.7.2,<0.8.0)
Requires-Dist: pydantic (>=2.9.0,<3.0.0)
Requires-Dist: pydantic-settings (>=2.4.0,<3.0.0)
Requires-Dist: selenium (>=4.24.0,<5.0.0)
Project-URL: Documentation, https://fmind.github.io/bromate/
Project-URL: Repository, https://github.com/fmind/bromate
